odoo10_addon_l10n_br_hr-10.0.0.0.0.99.dev22-nspkg.pth
odoo/addons/l10n_br_hr/README.rst
odoo/addons/l10n_br_hr/__init__.py
odoo/addons/l10n_br_hr/__manifest__.py
odoo/addons/l10n_br_hr/data/dependent_type_data.xml
odoo/addons/l10n_br_hr/data/hr_employee_data.xml
odoo/addons/l10n_br_hr/data/hr_employee_nationality_code_data.xml
odoo/addons/l10n_br_hr/data/l10n_br_hr.cbo.csv
odoo/addons/l10n_br_hr/i18n/l10n_br_hr.pot
odoo/addons/l10n_br_hr/models/__init__.py
odoo/addons/l10n_br_hr/models/hr_employee.py
odoo/addons/l10n_br_hr/models/hr_job.py
odoo/addons/l10n_br_hr/models/l10n_br_hr.py
odoo/addons/l10n_br_hr/models/res_company.py
odoo/addons/l10n_br_hr/security/ir.model.access.csv
odoo/addons/l10n_br_hr/static/description/icon.png
odoo/addons/l10n_br_hr/test/l10n_br_hr_demo.yml
odoo/addons/l10n_br_hr/views/hr_employee_dependent_view.xml
odoo/addons/l10n_br_hr/views/hr_employee_view.xml
odoo/addons/l10n_br_hr/views/hr_job_view.xml
odoo/addons/l10n_br_hr/views/l10n_br_hr_cbo_view.xml
odoo/addons/l10n_br_hr/views/res_company_view.xml
odoo10_addon_l10n_br_hr-10.0.0.0.0.99.dev22.dist-info/METADATA
odoo10_addon_l10n_br_hr-10.0.0.0.0.99.dev22.dist-info/WHEEL
odoo10_addon_l10n_br_hr-10.0.0.0.0.99.dev22.dist-info/namespace_packages.txt
odoo10_addon_l10n_br_hr-10.0.0.0.0.99.dev22.dist-info/top_level.txt
odoo10_addon_l10n_br_hr-10.0.0.0.0.99.dev22.dist-info/RECORD
